rustfrc-1.1.5.dist-info/METADATA
rustfrc-1.1.5.dist-info/WHEEL
rustfrc-1.1.5.dist-info/license_files/LICENSE
rustfrc/py.typed
rustfrc/split.py
rustfrc/__init__.py
rustfrc/rustfrc.cp311-win_amd64.pyd
rustfrc-1.1.5.dist-info/RECORD
