Metadata-Version: 2.3
Name: rustfrc
Version: 1.1.5
Classifier: Intended Audience :: Science/Research
Classifier: Programming Language :: Python
Classifier: Programming Language :: Rust
Classifier: Topic :: Scientific/Engineering :: Image Processing
Requires-Dist: numpy >=1.18 ; python_version < '3.12'
Requires-Dist: numpy >=1.26 ; python_version >= '3.12'
License-File: LICENSE
Summary: Fast utility functions useful for Fourier Ring/Shell Correlation: binom_split, pois_gen, square_abs.
Author: Tip ten Brink
Author-email: T.M.tenBrink@student.tudelft.nl
License: Apache-2.0
Requires-Python: >=3.8, <3.13
Project-URL: Source, https://github.com/tmtenbrink/rustfrc
